greendb.py
greenquery.py
greendb-0.2.4.dist-info/METADATA
greendb-0.2.4.dist-info/WHEEL
greendb-0.2.4.dist-info/top_level.txt
greendb-0.2.4.dist-info/RECORD
