Metadata-Version: 2.4
Name: greendb
Version: 0.2.4
Summary: database server powered by gevent and lmdb
Author-email: Charles Leifer <coleifer@gmail.com>
Project-URL: Repository, https://github.com/coleifer/greendb
Project-URL: Documentation, https://github.com/coleifer/greendb/blob/master/README.md
Classifier: Programming Language :: Python :: 2
Classifier: Programming Language :: Python :: 3
Classifier: Topic :: Software Development :: Libraries :: Python Modules
Requires-Dist: lmdb
Requires-Dist: msgpack-python
Requires-Dist: gevent
